Intel80386ChengxuyuanCankaoshouce/README.md
Intel80386ChengxuyuanCankaoshouce/__init__.py
Intel80386ChengxuyuanCankaoshouce/__main__.py
Intel80386ChengxuyuanCankaoshouce/file.epub
Intel80386ChengxuyuanCankaoshouce/index.html
Intel80386ChengxuyuanCankaoshouce/css/__init__.py
Intel80386ChengxuyuanCankaoshouce/css/annotations.css
Intel80386ChengxuyuanCankaoshouce/css/main.css
Intel80386ChengxuyuanCankaoshouce/css/normalize.css
Intel80386ChengxuyuanCankaoshouce/css/popup.css
Intel80386ChengxuyuanCankaoshouce/font/__init__.py
Intel80386ChengxuyuanCankaoshouce/font/fontello.eot
Intel80386ChengxuyuanCankaoshouce/font/fontello.svg
Intel80386ChengxuyuanCankaoshouce/font/fontello.ttf
Intel80386ChengxuyuanCankaoshouce/font/fontello.woff
Intel80386ChengxuyuanCankaoshouce/img/__init__.py
Intel80386ChengxuyuanCankaoshouce/img/annotator-glyph-sprite.png
Intel80386ChengxuyuanCankaoshouce/img/annotator-icon-sprite.png
Intel80386ChengxuyuanCankaoshouce/img/apple-touch-icon.png
Intel80386ChengxuyuanCankaoshouce/img/cancelfullscreen.png
Intel80386ChengxuyuanCankaoshouce/img/close.png
Intel80386ChengxuyuanCankaoshouce/img/fullscreen.png
Intel80386ChengxuyuanCankaoshouce/img/loader.gif
Intel80386ChengxuyuanCankaoshouce/img/menu-icon.png
Intel80386ChengxuyuanCankaoshouce/img/save.png
Intel80386ChengxuyuanCankaoshouce/img/saved.png
Intel80386ChengxuyuanCankaoshouce/img/settings-s.png
Intel80386ChengxuyuanCankaoshouce/img/settings.png
Intel80386ChengxuyuanCankaoshouce/img/star.png
Intel80386ChengxuyuanCankaoshouce/js/__init__.py
Intel80386ChengxuyuanCankaoshouce/js/epub.js
Intel80386ChengxuyuanCankaoshouce/js/epub.min.js
Intel80386ChengxuyuanCankaoshouce/js/epub.min.map
Intel80386ChengxuyuanCankaoshouce/js/hooks.min.js
Intel80386ChengxuyuanCankaoshouce/js/hooks.min.map
Intel80386ChengxuyuanCankaoshouce/js/reader.js
Intel80386ChengxuyuanCankaoshouce/js/reader.js.map
Intel80386ChengxuyuanCankaoshouce/js/reader.min.js
Intel80386ChengxuyuanCankaoshouce/js/reader.min.map
intel_80386_chengxuyuan_cankaoshouce-2024.3.1.0.dist-info/METADATA
intel_80386_chengxuyuan_cankaoshouce-2024.3.1.0.dist-info/WHEEL
intel_80386_chengxuyuan_cankaoshouce-2024.3.1.0.dist-info/entry_points.txt
intel_80386_chengxuyuan_cankaoshouce-2024.3.1.0.dist-info/top_level.txt
intel_80386_chengxuyuan_cankaoshouce-2024.3.1.0.dist-info/RECORD
